preswald/__init__.py
preswald/build.py
preswald/cli.py
preswald/deploy.py
preswald/main.py
preswald/utils.py
preswald/browser/__init__.py
preswald/browser/boot.js
preswald/browser/entrypoint.py
preswald/browser/virtual_service.py
preswald/engine/__init__.py
preswald/engine/base_service.py
preswald/engine/render_tracking.py
preswald/engine/runner.py
preswald/engine/server_service.py
preswald/engine/service.py
preswald/engine/telemetry.py
preswald/engine/utils.py
preswald/engine/managers/__init__.py
preswald/engine/managers/branding.py
preswald/engine/managers/data.py
preswald/engine/managers/layout.py
preswald/engine/transformers/__init__.py
preswald/engine/transformers/frame_context.py
preswald/engine/transformers/reactive_runtime.py
preswald/interfaces/__init__.py
preswald/interfaces/component_return.py
preswald/interfaces/components.py
preswald/interfaces/data.py
preswald/interfaces/dependency_tracker.py
preswald/interfaces/tracked_value.py
preswald/interfaces/workflow.py
preswald/interfaces/render/__init__.py
preswald/interfaces/render/registry.py
preswald/static/favicon.ico
preswald/static/index.html
preswald/static/logo.png
preswald/static/assets/index-BKwbY9jX.js
preswald/static/assets/index-DSk9O5xK.css
preswald/static/assets/worker-BYIHGkSJ.js
preswald/templates/hello.py.template
preswald/templates/preswald.toml.template
preswald/templates/sample.csv.template
preswald/templates/secrets.toml.template
preswald/tutorial/.gitignore
preswald/tutorial/README.md
preswald/tutorial/hello.py
preswald/tutorial/preswald.toml
preswald/tutorial/pyproject.toml
preswald/tutorial/data/sample.csv
preswald/tutorial/images/favicon.ico
preswald/tutorial/images/logo.png
preswald-0.1.59.dist-info/METADATA
preswald-0.1.59.dist-info/WHEEL
preswald-0.1.59.dist-info/entry_points.txt
preswald-0.1.59.dist-info/licenses/LICENSE
preswald-0.1.59.dist-info/RECORD
