Metadata-Version: 2.4
Name: preswald
Version: 0.1.59
Summary: A lightweight data workflow SDK
Author-email: Structured Labs <founders@structuredlabs.com>
License-Expression: Apache-2.0
License-File: LICENSE
Requires-Python: >=3.10
Requires-Dist: click>=8.1.7
Requires-Dist: duckdb>=1.1.2
Requires-Dist: fastapi<1.0.0,>=0.68.0; platform_system != 'Emscripten'
Requires-Dist: httpx<1.0.0,>=0.23.0
Requires-Dist: jinja2>=3.1.3
Requires-Dist: markdown>=3.4.0
Requires-Dist: matplotlib>=3.8.4
Requires-Dist: msgpack~=1.1.0
Requires-Dist: networkx>=3.0
Requires-Dist: pandas>=1.5
Requires-Dist: plotly==5.24.1
Requires-Dist: python-multipart<0.1.0,>=0.0.5
Requires-Dist: requests>=2.31.0
Requires-Dist: scipy>=1.15.2; platform_system != 'Emscripten'
Requires-Dist: toml==0.10.2
Requires-Dist: tomli>=2.0.1
Requires-Dist: uvicorn<1.0.0,>=0.15.0; platform_system != 'Emscripten'
Requires-Dist: websockets<11.0,>=10.0; platform_system != 'Emscripten'
Provides-Extra: dev
Requires-Dist: build; extra == 'dev'
Requires-Dist: pre-commit>=3.5.0; extra == 'dev'
Requires-Dist: pytest>=8.3; extra == 'dev'
Requires-Dist: ruff>=0.1.11; extra == 'dev'
Requires-Dist: twine; extra == 'dev'
Provides-Extra: playwright
Requires-Dist: playwright<2.0.0,>=1.15.0; (platform_system != 'Emscripten') and extra == 'playwright'
